Workbook

Sheet Student

Sheet Financial_Data
A1: Year | B1: Net Revenue | C1: Operating Income (EBIT) | D1: Income before tax (EBT) | E1: Net income | G1: Total Assets | H1: Total Shareholder's Equity | J1: Net cash from operating activities | K1: Capital expenditures | L1: Depreciation & amortisation | N1: Net profit margin | O1: Asset turnover | P1: Equity multiplier | Q1: Cash conversion ratio | R1: Return on Equity (ROE) | S1: Free Cash Flow | T1: Operating Current Assets | U1: Operating Current Liabilities | V1: Net Working Capital | Y1: Operating Margin | Z1: ROA
A2: 2020 | B2: 21846 | C2: 14081 | D2: 13754 | E2: 10866 | G2: 80919 | H2: 36210 | J2: 10440 | K2: 736 | L2: 767 | N2: =E2/B2 -> 0.49739083 | O2: =B2/G2 -> 0.26997368 | P2: =G2/H2 -> 2.2347142 | Q2: =J2/E2 -> 0.96079514 | R2: =N2*O2*P2*Q2 -> 0.28831814 | S2: =J2-K2 -> 9704 | Y2: =Financial_Data!C2/Financial_Data!B2 -> 0.64455736 | Z2: =Financial_Data!E2/Financial_Data!G2 -> 0.13428243
A3: 2021 | B3: 24105 | C3: 15804 | D3: 16063 | E3: 12311 | G3: 82896 | H3: 37589 | J3: 15227 | K3: 705 | L3: 804 | N3: =E3/B3 -> 0.51072392 | O3: =B3/G3 -> 0.29078605 | P3: =G3/H3 -> 2.205326 | Q3: =J3/E3 -> 1.2368613 | R3: =N3*O3*P3*Q3 -> 0.40509192 | S3: =J3-K3 -> 14522 | Y3: =Financial_Data!C3/Financial_Data!B3 -> 0.65563161 | Z3: =Financial_Data!E3/Financial_Data!G3 -> 0.14851139
A4: 2022 | B4: 29310 | C4: 18813 | D4: 18136 | E4: 14957 | G4: 85501 | H4: 35581 | J4: 18849 | K4: 970 | L4: 861 | N4: =E4/B4 -> 0.51030365 | O4: =B4/G4 -> 0.34280301 | P4: =G4/H4 -> 2.402996 | Q4: =J4/E4 -> 1.2602126 | R4: =N4*O4*P4*Q4 -> 0.52974902 | S4: =J4-K4 -> 17879 | Y4: =Financial_Data!C4/Financial_Data!B4 -> 0.64186285 | Z4: =Financial_Data!E4/Financial_Data!G4 -> 0.17493363
A5: 2023 | B5: 32653 | C5: 21000 | D5: 21037 | E5: 17273 | G5: 90499 | H5: 38492 | J5: 20755 | K5: 1059 | L5: 943 | N5: =E5/B5 -> 0.52898662 | O5: =B5/G5 -> 0.36081062 | P5: =G5/H5 -> 2.3511119 | Q5: =J5/E5 -> 1.2015863 | R5: =N5*O5*P5*Q5 -> 0.53920295 | S5: =J5-K5 -> 19696 | T5: 8635 | U5: 18342 | V5: =T5-U5 -> -9707 | Y5: =Financial_Data!C5/Financial_Data!B5 -> 0.64312621 | Z5: =Financial_Data!E5/Financial_Data!G5 -> 0.19086399
A6: 2024 | B6: 35926 | C6: 23595 | D6: 23916 | E6: 19743 | G6: 94511 | H6: 39137 | J6: 19950 | K6: 1257 | L6: 1034 | N6: =E6/B6 -> 0.54954629 | O6: =B6/G6 -> 0.38012506 | P6: =G6/H6 -> 2.4148759 | Q6: =J6/E6 -> 1.0104847 | R6: =N6*O6*P6*Q6 -> 0.50974781 | S6: =J6-K6 -> 18693 | T6: 12245 | U6: 21266 | V6: =T6-U6 -> -9021 | W6: ΔNWC 2024 | X6: =V6-V5 -> 686 | Y6: =Financial_Data!C6/Financial_Data!B6 -> 0.65676669 | Z6: =Financial_Data!E6/Financial_Data!G6 -> 0.20889632

Sheet Visa_DCF
A1: Base Year | B1: Year | C1: Revenue | D1: EBIT | E1: Tax Rate | F1: NOPAT | G1: D&A | H1: CapEX | I1: ΔNWC | J1: FCFF | N1: WACC inputs
A2: 0 | B2: 2024 | C2: =Financial_Data!B6 -> 35926 | D2: =Financial_Data!C6 -> 23595 | E2: 0.165 | F2: =D2*(1-E2) -> 19701.825 | G2: =Financial_Data!L6 -> 1034 | H2: =Financial_Data!K6 -> 1257 | I2: =Financial_Data!X6 -> 686 | J2: =F2+G2-H2-I2 -> 18792.825 | K2: Discount Factor | L2: PV(FCFF) | M2: Valuation date | N2: 45565
A3: 1 | B3: 2025 | C3: =C2*(1+8%) -> 38800.08 | D3: =C3*65.7% -> 25491.653 | E3: 0.165 | F3: =D3*(1-E3) -> 21285.53 | G3: =C3*2.9% -> 1125.2023 | H3: =C3*3.5% -> 1358.0028 | I3: =(C3-C2)*1.9% -> 54.60752 | J3: =F3+G3-H3-I3 -> 20998.122 | K3: =1/(1+$N$15)^$A3 -> 0.92243865 | L3: =$J3*$K3 -> 19369.479 | M3: Risk-free rate (Rf) | N3: 0.0412
A4: 2 | B4: 2026 | C4: =C3*(1+7%) -> 41516.086 | D4: =C4*65.7% -> 27276.068 | E4: 0.165 | F4: =D4*(1-E4) -> 22775.517 | G4: =C4*2.9% -> 1203.9665 | H4: =C4*3.5% -> 1453.063 | I4: =(C4-C3)*1.9% -> 51.604106 | J4: =F4+G4-H4-I4 -> 22474.816 | K4: =1/(1+$N$15)^$A4 -> 0.85089306 | L4: =$J4*$K4 -> 19123.665 | M4: Equity risk premium | N4: 0.055
A5: 3 | B5: 2027 | C5: =C4*(1+6%) -> 44007.051 | D5: =C5*65.7% -> 28912.632 | E5: 0.165 | F5: =D5*(1-E5) -> 24142.048 | G5: =C5*2.9% -> 1276.2045 | H5: =C5*3.5% -> 1540.2468 | I5: =(C5-C4)*1.9% -> 47.328338 | J5: =F5+G5-H5-I5 -> 23830.677 | K5: =1/(1+$N$15)^$A5 -> 0.78489664 | L5: =$J5*$K5 -> 18704.619 | M5: Beta (levered) | N5: 0.82
A6: 4 | B6: 2028 | C6: =C5*(1+5.5%) -> 46427.439 | D6: =C6*65.7% -> 30502.827 | E6: 0.165 | F6: =D6*(1-E6) -> 25469.861 | G6: =C6*2.9% -> 1346.3957 | H6: =C6*3.5% -> 1624.9603 | I6: =(C6-C5)*1.9% -> 45.987368 | J6: =F6+G6-H6-I6 -> 25145.309 | K6: =1/(1+$N$15)^$A6 -> 0.724019 | L6: =$J6*$K6 -> 18205.681 | M6: Cost of equity | N6: =N3+N5*N4 -> 0.0863
A7: 5 | B7: 2029 | C7: =C6*(1+5%) -> 48748.81 | D7: =C7*65.7% -> 32027.968 | E7: 0.165 | F7: =D7*(1-E7) -> 26743.354 | G7: =C7*2.9% -> 1413.7155 | H7: =C7*3.5% -> 1706.2084 | I7: =(C7-C6)*1.9% -> 44.106067 | J7: =F7+G7-H7-I7 -> 26406.755 | K7: =1/(1+$N$15)^$A7 -> 0.6678631 | L7: =$J7*$K7 -> 17636.097 | M7: Total debt | N7: 20836
M8: Market cap | N8: 551540
M9: Debt weight | N9: =N7/(N7+N8) -> 0.036402644
M10: Equity weight | N10: =N8/(N7+N8) -> 0.96359736
M11: Tax rate | N11: =(Financial_Data!D6 - Financial_Data!E6)/Financial_Data!D6 -> 0.1744857
M12: Interest expense | N12: =ABS(641) -> 641
M13: Avg debt | N13: 20836
M14: Pre-tax cost of debt | N14: =ABS(N12)/N13 -> 0.030764062
M15: WACC | N15: =N10*N6 + N9*N14*(1-N11) -> 0.08408294
M16: Terminal growth (g) | N16: 0.025
M17: FCFF 2030 | N17: =J7*(1+$N$16) -> 27066.924
M18: Terminal value at 2029 | N18: =$J$7*(1+$N$16)/($N$15-$N$16) -> 458117.42
M19: PV Terminal Value | N19: =$N$18*K7 -> 305959.72
M20: Enterprise Value (EV) | N20: =SUM($L$3:$L$7)+N19 -> 398999.26
M21: Cash (FY2024) | N21: 11975
M22: Net debt (Debt - Cash) | N22: =$N$7-$N$21 -> 8861
M23: Equity value | N23: =$N$20-$N$22 -> 390138.26
M24: Shares outstanding (millions) | N24: 1733
M25: Value per share | N25: =$N$23/$N$24 -> 225.12306
B28: =N25 -> 225.12306 | C28: 0.015 | D28: 0.02 | E28: 0.025 | F28: 0.03 | G28: 0.035
B29: 0.07 | C29: 251.19062 | D29: 272.32642 | E29: 298.15907 | F29: 330.44987 | G29: 371.96662
B30: 0.075 | C30: 229.47977 | D30: 246.76753 | E30: 267.51283 | F30: 292.86821 | G30: 324.56244
B31: 0.08 | C31: 211.11479 | D31: 225.47388 | E31: 242.44371 | F31: 262.80751 | G31: 287.69659
B32: 0.085 | C32: 195.3786 | D32: 207.46108 | E32: 221.55731 | F32: 238.21649 | G32: 258.2075 | N32: All monetary values are in USD millions unless stated otherwise.
B33: 0.09 | C33: 181.74532 | D33: 192.02598 | E33: 203.88829 | F33: 217.72764 | G33: 234.08325 | N33: Over 75% of EV comes from terminal value.
B34: 0.095 | C34: 169.82055 | D34: 178.65295 | E34: 188.74712 | F34: 200.39424 | G34: 213.98255 | N34: The cost of debt is approximated using accounting interest expense due to limited market yield data.
B35: 0.1 | C35: 159.3027 | D35: 166.95526 | E35: 175.62816 | F35: 185.54005 | G35: 196.97685

Sheet Competitors
A1: Company | B1: Profit Margin | C1: Operating Margin | D1: ROE | E1: ROA
A2: VISA | B2: =Financial_Data!N6 -> 0.54954629 | C2: =Financial_Data!Y6 -> 0.65676669 | D2: =Financial_Data!R6 -> 0.50974781 | E2: =Financial_Data!Z6 -> 0.20889632
A3: Mastercard | B3: 0.4463 | C3: 0.5532 | D3: 1.919 | E3: 0.284
A4: AmEx | B4: 0.1347 | C4: 0.1955 | D4: 0.3414 | E4: 0.037
A5: Paypal | B5: 0.143 | C5: 0.1675 | D5: 0.2031 | E5: 0.051

Sheet Charts
